config/cli/__init__.py
config/cli/main.py
config/cli/py.typed
config/common/__init__.py
config/common/files.py
config/common/py.typed
config/env/__init__.py
config/env/py.typed
config/errors/__init__.py
config/errors/py.typed
config/ini/__init__.py
config/ini/py.typed
config/json/__init__.py
config/json/py.typed
config/toml/__init__.py
config/toml/py.typed
config/user/__init__.py
config/user/cli.py
config/user/py.typed
config/yaml/__init__.py
config/yaml/py.typed
essentials_configuration-2.0.4.dist-info/METADATA
essentials_configuration-2.0.4.dist-info/WHEEL
essentials_configuration-2.0.4.dist-info/entry_points.txt
essentials_configuration-2.0.4.dist-info/licenses/LICENSE
essentials_configuration-2.0.4.dist-info/RECORD
