Metadata-Version: 2.1
Name: essentials-configuration
Version: 2.0.4
Summary: Implementation of key-value pair based configuration for Python applications.
Project-URL: Homepage, https://github.com/Neoteroi/essentials-configuration
Project-URL: Bug Tracker, https://github.com/Neoteroi/essentials-configuration/issues
Author-email: Roberto Prevato <roberto.prevato@gmail.com>
License-File: LICENSE
Keywords: configuration,management,root,settings,strategy
Classifier: Development Status :: 5 - Production/Stable
Classifier: License :: OSI Approved :: MIT License
Classifier: Operating System :: OS Independent
Classifier: Programming Language :: Python :: 3
Classifier: Programming Language :: Python :: 3.8
Classifier: Programming Language :: Python :: 3.9
Classifier: Programming Language :: Python :: 3.10
Classifier: Programming Language :: Python :: 3.11
Classifier: Programming Language :: Python :: 3.12
Requires-Python: >=3.7
Requires-Dist: deepmerge~=1.1.0
Requires-Dist: python-dotenv~=1.0.0
Requires-Dist: tomli; python_version < '3.11'
Provides-Extra: full
Requires-Dist: pyyaml; extra == 'full'
Requires-Dist: rich-click; extra == 'full'
Provides-Extra: yaml
Requires-Dist: pyyaml; extra == 'yaml'
